LICENSE
README.md
package_info.json
setup.py
th2_grpc_sim_template/__init__.py
th2_grpc_sim_template/py.typed
th2_grpc_sim_template/sim_template.proto
th2_grpc_sim_template/sim_template_pb2.py
th2_grpc_sim_template/sim_template_pb2.pyi
th2_grpc_sim_template/sim_template_pb2_grpc.py
th2_grpc_sim_template/sim_template_service.py
th2_grpc_sim_template.egg-info/PKG-INFO
th2_grpc_sim_template.egg-info/SOURCES.txt
th2_grpc_sim_template.egg-info/dependency_links.txt
th2_grpc_sim_template.egg-info/requires.txt
th2_grpc_sim_template.egg-info/top_level.txt